flask_jaeger/__init__.py
flask_jaeger/constants.py
flask_jaeger/src.py
flask_jaeger-1.0.1.dist-info/LICENSE
flask_jaeger-1.0.1.dist-info/METADATA
flask_jaeger-1.0.1.dist-info/WHEEL
flask_jaeger-1.0.1.dist-info/top_level.txt
flask_jaeger-1.0.1.dist-info/RECORD
