Metadata-Version: 2.1
Name: flask-jaeger
Version: 1.0.1
Summary: flask jaeger
Home-page: UNKNOWN
Author: yuzhang
Author-email: geasyheart@163.com
License: UNKNOWN
Platform: UNKNOWN
Requires-Dist: Flask
Requires-Dist: jaeger-client (==4.4.0)
